AUTHORS
CHANGELOG.md
COPYING
MANIFEST.in
README.md
requirements-dev.txt
requirements-optional.txt
requirements.txt
setup.py
trezorctl
bash_completion.d/trezorctl.sh
tools/build_protobuf
tools/deserialize_tx.py
tools/encfs_aes_getpass.py
tools/helloworld.py
tools/mem_flashblock.py
tools/mem_read.py
tools/mem_write.py
tools/mnemonic_check.py
tools/pb2py
tools/pwd_reader.py
tools/rng_entropy_collector.py
tools/signtest.py
trezor_komodo.egg-info/PKG-INFO
trezor_komodo.egg-info/SOURCES.txt
trezor_komodo.egg-info/dependency_links.txt
trezor_komodo.egg-info/not-zip-safe
trezor_komodo.egg-info/requires.txt
trezor_komodo.egg-info/top_level.txt
trezorlib/__init__.py
trezorlib/_ed25519.py
trezorlib/ckd_public.py
trezorlib/client.py
trezorlib/coins.json
trezorlib/coins.py
trezorlib/cosi.py
trezorlib/debuglink.py
trezorlib/device.py
trezorlib/log.py
trezorlib/mapping.py
trezorlib/nem.py
trezorlib/protobuf.py
trezorlib/protocol_v1.py
trezorlib/protocol_v2.py
trezorlib/stellar.py
trezorlib/tools.py
trezorlib/tx_api.py
trezorlib/__pycache__/__init__.cpython-36.pyc
trezorlib/messages/Address.py
trezorlib/messages/ApplyFlags.py
trezorlib/messages/ApplySettings.py
trezorlib/messages/BackupDevice.py
trezorlib/messages/ButtonAck.py
trezorlib/messages/ButtonRequest.py
trezorlib/messages/ButtonRequestType.py
trezorlib/messages/Cancel.py
trezorlib/messages/ChangePin.py
trezorlib/messages/CipherKeyValue.py
trezorlib/messages/CipheredKeyValue.py
trezorlib/messages/ClearSession.py
trezorlib/messages/CosiCommit.py
trezorlib/messages/CosiCommitment.py
trezorlib/messages/CosiSign.py
trezorlib/messages/CosiSignature.py
trezorlib/messages/DebugLinkDecision.py
trezorlib/messages/DebugLinkFlashErase.py
trezorlib/messages/DebugLinkGetState.py
trezorlib/messages/DebugLinkLog.py
trezorlib/messages/DebugLinkMemory.py
trezorlib/messages/DebugLinkMemoryRead.py
trezorlib/messages/DebugLinkMemoryWrite.py
trezorlib/messages/DebugLinkState.py
trezorlib/messages/DebugLinkStop.py
trezorlib/messages/DecryptMessage.py
trezorlib/messages/DecryptedMessage.py
trezorlib/messages/ECDHSessionKey.py
trezorlib/messages/EncryptMessage.py
trezorlib/messages/EncryptedMessage.py
trezorlib/messages/Entropy.py
