Metadata-Version: 2.1
Name: trezor-komodo
Version: 0.10.2.post1
Summary: Python library for communicating with TREZOR Hardware Wallet
Home-page: https://github.com/KomodoPlatform/python-trezor
Author: KomodoPlatform
Author-email: alysakov@komodoplatform.com
License: LGPLv3
Platform: UNKNOWN
Classifier: License :: OSI Approved :: GNU Lesser General Public License v3 (LGPLv3)
Classifier: Operating System :: POSIX :: Linux
Classifier: Operating System :: Microsoft :: Windows
Classifier: Operating System :: MacOS :: MacOS X
Classifier: Programming Language :: Python :: 3 :: Only
Requires-Python: >=3.3
Provides-Extra: hidapi
Provides-Extra: ethereum
